tweety/__init__.py
tweety/auth.py
tweety/bot.py
tweety/builder.py
tweety/constants.py
tweety/exceptions.py
tweety/exceptions_.py
tweety/filters.py
tweety/http.py
tweety/session.py
tweety/transaction.py
tweety/updates.py
tweety/user.py
tweety/utils.py
tweety/captcha/__init__.py
tweety/captcha/anticaptcha.py
tweety/captcha/base.py
tweety/captcha/capsolver.py
tweety/captcha/two_captcha.py
tweety/events/__init__.py
tweety/events/base.py
tweety/events/newmessage.py
tweety/events/stream_event.py
tweety/types/__init__.py
tweety/types/base.py
tweety/types/bookmarks.py
tweety/types/community.py
tweety/types/follow.py
tweety/types/gifs.py
tweety/types/grok.py
tweety/types/inbox.py
tweety/types/likes.py
tweety/types/lists.py
tweety/types/mentions.py
tweety/types/n_types.py
tweety/types/notification.py
tweety/types/places.py
tweety/types/retweets.py
tweety/types/search.py
tweety/types/topic.py
tweety/types/twDataTypes.py
tweety/types/usertweet.py
tweety_ns-2.4.1.dist-info/METADATA
tweety_ns-2.4.1.dist-info/WHEEL
tweety_ns-2.4.1.dist-info/top_level.txt
tweety_ns-2.4.1.dist-info/RECORD
