Metadata-Version: 2.4
Name: tweety-ns
Version: 2.4.1
Summary: An easy Twitter Scraper
Home-page: https://github.com/mahrtayyab/tweety
Author: Tayyab Kharl
Author-email: tayyabmahr@gmail.com
License: MIT
Project-URL: Bug Tracker, https://github.com/mahrtayyab/tweety/issues
Project-URL: Documentation, https://github.com/mahrtayyab/tweety
Keywords: TWITTER,TWITTER SCRAPE,SCRAPE TWEETS
Classifier: Development Status :: 4 - Beta
Classifier: Intended Audience :: Developers
Classifier: Topic :: Software Development :: Build Tools
Classifier: Programming Language :: Python :: 3
Requires-Python: >=3.9
Requires-Dist: beautifulsoup4[lxml]~=4.12
Requires-Dist: openpyxl
Requires-Dist: httpx[http2]
Requires-Dist: dateutils
Requires-Dist: anticaptchaofficial
Requires-Dist: capsolver
Requires-Dist: 2captcha-python
Requires-Dist: python-magic
Requires-Dist: python-magic-bin; platform_system == "Windows"
Dynamic: author
Dynamic: author-email
Dynamic: classifier
Dynamic: home-page
Dynamic: keywords
Dynamic: license
Dynamic: requires-dist
Dynamic: summary
